qorange/__init__.py
qorange/circuits.py
qorange/gates.py
qorange-1.0.0.dist-info/LICENSE
qorange-1.0.0.dist-info/METADATA
qorange-1.0.0.dist-info/WHEEL
qorange-1.0.0.dist-info/top_level.txt
qorange-1.0.0.dist-info/RECORD
